txtrader/__init__.py
txtrader/__main__.py
txtrader/client.py
txtrader/config.py
txtrader/daemon.py
txtrader/rtx.py
txtrader/tcpserver.py
txtrader/txtrader.tac
txtrader/version.py
txtrader/webserver.py
txTrader-1.14.29.dist-info/AUTHORS
txTrader-1.14.29.dist-info/LICENSE
txTrader-1.14.29.dist-info/METADATA
txTrader-1.14.29.dist-info/WHEEL
txTrader-1.14.29.dist-info/entry_points.txt
txTrader-1.14.29.dist-info/top_level.txt
txTrader-1.14.29.dist-info/RECORD
